conan/__init__.py
conan/conan.py
conan_tool-1.0.2.dist-info/METADATA
conan_tool-1.0.2.dist-info/WHEEL
conan_tool-1.0.2.dist-info/top_level.txt
conan_tool-1.0.2.dist-info/RECORD
